ms2ml/__init__.py
ms2ml/annotation_classes.py
ms2ml/config.py
ms2ml/constants.py
ms2ml/data/__init__.py
ms2ml/data/adapters/__init__.py
ms2ml/data/adapters/base.py
ms2ml/data/adapters/bibliospec.py
ms2ml/data/adapters/encyclopedia.py
ms2ml/data/adapters/fasta.py
ms2ml/data/adapters/mokapot.py
ms2ml/data/adapters/msp.py
ms2ml/data/adapters/mzml.py
ms2ml/data/adapters/pin.py
ms2ml/data/adapters/spectronaut.py
ms2ml/data/parsing/__init__.py
ms2ml/data/parsing/base.py
ms2ml/data/parsing/bibliospec.py
ms2ml/data/parsing/encyclopedia.py
ms2ml/data/parsing/fasta.py
ms2ml/data/parsing/mokapot.py
ms2ml/data/parsing/msp.py
ms2ml/data/parsing/pin.py
ms2ml/data/parsing/spectronaut.py
ms2ml/isoform_utils.py
ms2ml/landmarks.py
ms2ml/metrics/base.py
ms2ml/peptide.py
ms2ml/proforma_utils.py
ms2ml/spectrum.py
ms2ml/type_defs.py
ms2ml/unimod/__init__.py
ms2ml/unimod/unimod.xml
ms2ml/utils/__init__.py
ms2ml/utils/class_utils.py
ms2ml/utils/mz_utils.py
ms2ml/utils/tensor_utils.py
ms2ml-0.0.46.dist-info/LICENSE
ms2ml-0.0.46.dist-info/METADATA
ms2ml-0.0.46.dist-info/WHEEL
ms2ml-0.0.46.dist-info/RECORD
