Metadata-Version: 2.1
Name: ms2ml
Version: 0.0.46
Summary: Provides an intermediate layer between mass spec data and ML applications, such as encoding.
Home-page: https://jspaezp.github.io/ms2ml/main
License: Apache 2.0
Author: J. Sebastian Paez
Author-email: jspaezp@users.noreply.github.com
Requires-Python: >3.9,<3.14
Classifier: License :: Other/Proprietary License
Classifier: Programming Language :: Python :: 3
Classifier: Programming Language :: Python :: 3.10
Classifier: Programming Language :: Python :: 3.11
Classifier: Programming Language :: Python :: 3.12
Requires-Dist: appdirs (>=1.4.4,<2.0.0)
Requires-Dist: importlib-metadata (>=6,<9)
Requires-Dist: lark (>=1.1.2,<2.0.0)
Requires-Dist: loguru (>=0.6,<0.8)
Requires-Dist: lxml (>=4.9.1,<5.0.0)
Requires-Dist: numpy (>=2.0.2,<3.0.0)
Requires-Dist: pandas (>=2.0.1,<3.0.0)
Requires-Dist: pandas-stubs (>=2.0.2.230605,<3.0.0.0) ; python_version >= "3.8" and python_version < "3.11"
Requires-Dist: psims (>=1.2.3,<2.0.0)
Requires-Dist: pyteomics (>=4.6.3,<5.0.0)
Requires-Dist: tomli (>=2.0.1,<3.0.0)
Requires-Dist: tomli-w (>=1.0.0,<2.0.0)
Requires-Dist: tqdm (>=4.64.1,<5.0.0)
Requires-Dist: uniplot (>=0.10.2,<0.11.0)
Project-URL: Repository, https://github.com/jspaezp/ms2ml
